[{"description":"The LeaderZ Conference aims to redefine the way secondary school prefects are trained, mentored, and empowered.","is_featured":true,"title":"LeaderZ Conferences","image_data":null,"id":"c358aea5-7694-4e70-b789-2f56dea33224","created_at":"2026-03-07T20:47:16.701412+01:00"},{"description":"Designed to inspire aspiring leaders to position themselves with the requisite knowledge and values required to address national challenges.","is_featured":true,"title":"Nation Building Conferences","image_data":null,"id":"063e13bc-14d9-4204-a256-6c4796d135d8","created_at":"2026-03-07T20:47:16.701460+01:00"},{"description":"A transformative learning experience empowering mentors and mentees.","is_featured":true,"title":"Mentorship Hub","image_data":null,"id":"17f8dc4c-8996-41f0-9bae-edb4df471d00","created_at":"2026-03-07T20:47:16.701499+01:00"}]